playlist_length
