Metadata-Version: 2.1
Name: playlist-length
Version: 1.8.1
Summary: A command-line tool to get length of all audios/videos in a directory
Home-page: http://github.com/karansthr/playlist-length
Author: Karan Suthar
Author-email: karansthr97@gmail.com
License: MIT License
Project-URL: Bug Reports, https://github.com/karansthr/playlist-length/issues
Project-URL: Source, https://github.com/karansthr/playlist-length/
Project-URL: Blog, https://fosstack.com/tips/videos-playlist-length-calculator/
Project-URL: About, https://fosstack.com/about/
Keywords: videolength playlist-length
Platform: UNKNOWN
